pysnmp_apps/__init__.py
pysnmp_apps/error.py
pysnmp_apps/cli/__init__.py
pysnmp_apps/cli/base.py
pysnmp_apps/cli/main.py
pysnmp_apps/cli/mibview.py
pysnmp_apps/cli/msgmod.py
pysnmp_apps/cli/pdu.py
pysnmp_apps/cli/secmod.py
pysnmp_apps/cli/spark.py
pysnmp_apps/cli/target.py
pysnmp_apps-0.5.3.data/scripts/snmpbulkwalk.py
pysnmp_apps-0.5.3.data/scripts/snmpget.py
pysnmp_apps-0.5.3.data/scripts/snmpset.py
pysnmp_apps-0.5.3.data/scripts/snmptranslate.py
pysnmp_apps-0.5.3.data/scripts/snmptrap.py
pysnmp_apps-0.5.3.data/scripts/snmpwalk.py
pysnmp_apps-0.5.3.dist-info/DESCRIPTION.rst
pysnmp_apps-0.5.3.dist-info/METADATA
pysnmp_apps-0.5.3.dist-info/RECORD
pysnmp_apps-0.5.3.dist-info/WHEEL
pysnmp_apps-0.5.3.dist-info/metadata.json
pysnmp_apps-0.5.3.dist-info/top_level.txt
pysnmp_apps-0.5.3.dist-info/zip-safe
